isoncorrect/__init__.py
isoncorrect/correct_seqs.py
isoncorrect/create_augmented_reference.py
isoncorrect/help_functions.py
isoncorrect/isONcorrect.py
isoncorrect/run_isoncorrect.py
isONcorrect-0.1.3.5.dist-info/LICENSE.txt
isONcorrect-0.1.3.5.dist-info/METADATA
isONcorrect-0.1.3.5.dist-info/WHEEL
isONcorrect-0.1.3.5.dist-info/entry_points.txt
isONcorrect-0.1.3.5.dist-info/top_level.txt
isONcorrect-0.1.3.5.dist-info/RECORD
