Metadata-Version: 2.1
Name: isONcorrect
Version: 0.1.3.5
Summary: De novo error-correction of long-read transcriptome reads
Home-page: https://github.com/ksahlin/isONcorrect
Author: Kristoffer Sahlin
Author-email: Kristoffer Sahlin <krsahlin.work@gmail.com>
Project-URL: Homepage, https://github.com/ksahlin/isONcorrect
Project-URL: Bug Tracker, https://github.com/ksahlin/isONcorrect/issues
Classifier: Programming Language :: Python :: 3
Classifier: License :: OSI Approved :: MIT License
Classifier: Operating System :: OS Independent
Requires-Python: !=3.0.*, !=3.1.*, !=3.2.*, !=3.3.*, <4
License-File: LICENSE.txt
Requires-Dist: edlib >=1.1.2
Requires-Dist: numpy >=1.16.2
Requires-Dist: parasail ==1.3.4
